robomasterpy/__init__.py
robomasterpy/__version__.py
robomasterpy/client.py
robomasterpy/framework.py
robomasterpy/measure.py
robomasterpy-0.1.1.dist-info/LICENSE
robomasterpy-0.1.1.dist-info/METADATA
robomasterpy-0.1.1.dist-info/WHEEL
robomasterpy-0.1.1.dist-info/top_level.txt
robomasterpy-0.1.1.dist-info/RECORD
