Metadata-Version: 2.1
Name: robomasterpy
Version: 0.1.1
Summary: RoboMaster Python SDK and framework.
Home-page: https://github.com/nanmu42/robomasterpy
Author: LI Zhennan
Author-email: i@nanmu.me
License: MIT
Platform: UNKNOWN
Classifier: Framework :: Robot Framework
Classifier: Framework :: Robot Framework :: Library
Classifier: Framework :: Robot Framework :: Tool
Classifier: License :: OSI Approved :: MIT License
Classifier: Programming Language :: Python
Classifier: Programming Language :: Python :: 3
Classifier: Programming Language :: Python :: 3.6
Classifier: Programming Language :: Python :: 3.7
Classifier: Programming Language :: Python :: Implementation :: CPython
Classifier: Programming Language :: Python :: Implementation :: PyPy
Requires-Python: >=3.6.0
Provides-Extra: python 3.6.x needs
Provides-Extra: suggested flavor of OpenCV if you are not using conda
